solas_disparity.cpython-311-x86_64-linux-gnu.so
solas_disparity/__init__.pyi
solas_disparity/_ui.pyi
solas_disparity/const.pyi
solas_disparity/demographic_estimation/__init__.pyi
solas_disparity/demographic_estimation/_cache.pyi
solas_disparity/demographic_estimation/_demographic_estimation.pyi
solas_disparity/demographic_estimation/_gender_estimation.pyi
solas_disparity/demographic_estimation/_minority_estimation.pyi
solas_disparity/demographic_estimation/_race_estimation.pyi
solas_disparity/demographic_estimation/_zip9_mixin.pyi
solas_disparity/demographic_estimation/_zip_validations.pyi
solas_disparity/disparity/__init__.pyi
solas_disparity/disparity/_adverse_impact_ratio.pyi
solas_disparity/disparity/_adverse_impact_ratio_by_quantile.pyi
solas_disparity/disparity/_categorical_adverse_impact_ratio.pyi
solas_disparity/disparity/_custom_disparity_metric.pyi
solas_disparity/disparity/_disparity_validations.pyi
solas_disparity/disparity/_false_discovery_rate.pyi
solas_disparity/disparity/_false_negative_rate.pyi
solas_disparity/disparity/_false_positive_rate.pyi
solas_disparity/disparity/_intersectional_adverse_impact_ratio.pyi
solas_disparity/disparity/_odds_ratio.pyi
solas_disparity/disparity/_precision.pyi
solas_disparity/disparity/_relative_rate.pyi
solas_disparity/disparity/_residual_standardized_mean_difference.pyi
solas_disparity/disparity/_scoring_impact_ratio.pyi
solas_disparity/disparity/_segmented_adverse_impact_ratio.pyi
solas_disparity/disparity/_selection_impact_ratio.pyi
solas_disparity/disparity/_standardized_mean_difference.pyi
solas_disparity/disparity/_true_negative_rate.pyi
solas_disparity/disparity/_true_positive_rate.pyi
solas_disparity/disparity/_wasserstein.pyi
solas_disparity/plots/__init__.pyi
solas_disparity/plots/_adverse_impact_ratio.pyi
solas_disparity/plots/_adverse_impact_ratio_by_quantile.pyi
solas_disparity/plots/_categorical_adverse_impact_ratio.pyi
solas_disparity/plots/_colors.pyi
solas_ai-0.6.0.dist-info/METADATA
solas_ai-0.6.0.dist-info/WHEEL
solas_ai-0.6.0.dist-info/RECORD
solas_ai-0.6.0.dist-info/licenses/LICENSE
